setup.py
cache_nuggets/__init__.py
cache_nuggets/lib.py
cache_nuggets/test.py
django_cache_nuggets.egg-info/PKG-INFO
django_cache_nuggets.egg-info/SOURCES.txt
django_cache_nuggets.egg-info/dependency_links.txt
django_cache_nuggets.egg-info/requires.txt
django_cache_nuggets.egg-info/top_level.txt