Metadata-Version: 1.0
Name: django-cache-nuggets
Version: 0.1.1
Summary: Useful utils for Django caching
Home-page: https://github.com/andymckay/django-cache-nuggets
Author: Andy McKay
Author-email: andym@mozilla.com
License: BSD
Platform: UNKNOWN
Classifier: Intended Audience :: Developers
Classifier: Natural Language :: English
Classifier: Operating System :: OS Independent
Classifier: Framework :: Django
